{
  "$schema": "https://biomejs.dev/schemas/2.2.5/schema.json",
  "vcs": {
    "enabled": false,
    "clientKind": "git",
    "useIgnoreFile": false
  },
  "files": {
    "ignoreUnknown": false,
    "includes": ["**"]
  },
  "formatter": {
    "enabled": true,
    "indentStyle": "space",
    "indentWidth": 2,
    "formatWithErrors": true
  },
  "assist": { "actions": { "source": { "organizeImports": "on" } } },
  "linter": {
    "enabled": true,
    "rules": {
      "nursery": {},
      "suspicious": {
        "noArrayIndexKey": "off",
        "noExplicitAny": "off"
      },
      "a11y": {
        "useAnchorContent": "off",
        "useKeyWithClickEvents": "off"
      },
      "recommended": true,
      "complexity": {
        "noUselessFragments": "off",
        "noForEach": "off"
      },
      "correctness": {
        "useExhaustiveDependencies": "off",
        "useUniqueElementIds": "warn",
        "useHookAtTopLevel": "error"
      },
      "style": {
        "noParameterAssign": "error",
        "useAsConstAssertion": "error",
        "useDefaultParameterLast": "error",
        "useEnumInitializers": "error",
        "useSelfClosingElements": "error",
        "useSingleVarDeclarator": "error",
        "noUnusedTemplateLiteral": "error",
        "useNumberNamespace": "error",
        "noInferrableTypes": "error",
        "noUselessElse": "error"
      }
    }
  },
  "javascript": {
    "formatter": {
      "semicolons": "asNeeded"
    }
  }
}
